[
    {
        "id": "23ggha6556",
        "name": "Panti Asuhan Al Fitra",
        "telepon": "081347665987",
        "address": "Jl. Udawa No.12, RT.001/RW.004, Arjuna, Kec. Cicendo, Kota Bandung, Jawa Barat 40172",
        "urlImg": "https://i.ibb.co/74NZFZF/alfitra.jpg"
    },
    {
        "id": "26tgha6xc6",
        "name": "Panti Sosial Asuhan Anak (Psaa) Fajar Harapan",
        "telepon": "(022) 2508879",
        "address": "Jl. Surapati No.107, Sukaluyu, Kec. Cibeunying Kaler, Kota Bandung, Jawa Barat 40132",
        "urlImg": "https://i.ibb.co/frfVCbL/fajar.jpg"
    },
    {
        "id": "61gdha6756",
        "name": "Panti Asuhan Khoerunnisa",
        "telepon": "082262529435",
        "address": "Jl. Pasirturi No.28, Sukaluyu, Kec. Cibeunying Kaler, Kota Bandung, Jawa Barat 40123",
        "urlImg": "https://i.ibb.co/ZXCsy52/khoerunnisa.jpg"
    },
    {
        "id": "17gvha056",
        "name": "Panti Yatim Indonesia",
        "telepon": "(022) 20452762",
        "address": "Jl. Cikutra Barat No.76, Sadang Serang, Kecamatan Coblong, Kota Bandung, Jawa Barat 40123",
        "urlImg": "https://i.ibb.co/G2GNz61/indo.jpg"
    },
    {
        "id": "44g1h88656",
        "name": "Panti Asuhan Tunas Harapan",
        "telepon": "(022) 7274594",
        "address": "Gg. Bastaman, Cikutra, Kec. Cibeunying Kidul, Kota Bandung, Jawa Barat 40124",
        "urlImg": "https://i.ibb.co/cLvj7Pc/harapan.jpg"
    }
]